{
    "name": "ui_dual_blob",
    "parameters": {
        "sync_interval_secs": {
            "type": "int",
            "default": 5
        },
        "sp_name": {
            "type": "string",
            "default": "Scratchpad"
        },
        "sp_button_name": {
            "type": "string",
            "default": "Run!"
        },
        "sp_prefix_name": {
            "type": "string",
            "default": "Prefix Answer?"
        },
        "sp_ace_lang": {
            "type": "string",
            "default": null
        },
        "sp_run_lang": {
            "type": "string",
            "default": null
        },
        "sp_run_wrapper": {
            "type": "string",
            "defualt": null
        },
        "sp_run_wrapper_globalextra": {
            "type": "boolean",
            "default": false
        },
        "sp_html_out": {
            "type": "boolean",
            "default": false
        }
    }
}
